.requires
.test-requires
LICENSE
MANIFEST.in
README.rst
nutjob.py
setup.py
test_nutjob.py
tox.ini
nutjob.egg-info/PKG-INFO
nutjob.egg-info/SOURCES.txt
nutjob.egg-info/dependency_links.txt
nutjob.egg-info/entry_points.txt
nutjob.egg-info/requires.txt
nutjob.egg-info/top_level.txt